README.md
setup.py
knitter/__init__.py
knitter/configure.py
knitter/datadriver.py
knitter/executor.py
knitter/library.py
knitter/logger.py
knitter/reportor.py
knitter/webelement.py
knitter.egg-info/PKG-INFO
knitter.egg-info/SOURCES.txt
knitter.egg-info/dependency_links.txt
knitter.egg-info/requires.txt
knitter.egg-info/top_level.txt