Metadata-Version: 1.2
Name: knitter
Version: 1.0.0
Summary: A Web Automation Test Framework Based On Selenium WebDriver
Home-page: https://github.com/hw712/knitter
Author: Henry Wang
Author-email: outsidematrix@126.com
Maintainer: Henry Wang
Maintainer-email: outsidematrix@126.com
License: BSD License
Platform: linux
Platform: windows
Classifier: License :: OSI Approved :: GNU General Public License v3 (GPLv3)
Classifier: Topic :: Software Development :: Testing
Classifier: Topic :: Software Development :: Quality Assurance
Classifier: Topic :: Software Development :: Libraries :: Application Frameworks
